Metadata-Version: 2.1
Name: nbpages
Version: 0.0.1.dev5
Summary: Tools to maintain a respository of Jupyter notebooks
Home-page: https://github.com/jckantor/nbpages
Author: jckantor
Author-email: Kantor.1@nd.edu
License: MIT
Platform: UNKNOWN
